README.md
setup.py
fdfs_client/__init__.py
fdfs_client/client.py
fdfs_client/connection.py
fdfs_client/exceptions.py
fdfs_client/fdfs_protol.py
fdfs_client/fdfs_test.py
fdfs_client/storage_client.py
fdfs_client/tracker_client.py
fdfs_client/utils.py
fdfs_client_py34.egg-info/PKG-INFO
fdfs_client_py34.egg-info/SOURCES.txt
fdfs_client_py34.egg-info/dependency_links.txt
fdfs_client_py34.egg-info/not-zip-safe
fdfs_client_py34.egg-info/top_level.txt