Metadata-Version: 1.2
Name: fdfs-client-py34
Version: 0.1
Summary: The fdfs_client package for python3
Home-page: https://github.com/Greybeetle/My_Pypi
Author: greybeetle
Author-email: hanxuan_g@163.com
License: UNKNOWN
Platform: UNKNOWN
Requires-Python: >=3.4.0
